isage_neuromem-0.2.1.1.dist-info/licenses/LICENSE
sage/neuromem/__init__.py
sage/neuromem/_version.py
sage/neuromem/memory_manager.py
sage/neuromem/config/collection_config.py
sage/neuromem/memory_collection/__init__.py
sage/neuromem/memory_collection/collections_with_features.py
sage/neuromem/memory_collection/paper_features.py
sage/neuromem/memory_collection/unified_collection.py
sage/neuromem/memory_collection/indexes/__init__.py
sage/neuromem/memory_collection/indexes/base_index.py
sage/neuromem/memory_collection/indexes/bm25_index.py
sage/neuromem/memory_collection/indexes/faiss_index.py
sage/neuromem/memory_collection/indexes/fifo_queue_index.py
sage/neuromem/memory_collection/indexes/graph_index.py
sage/neuromem/memory_collection/indexes/index_factory.py
sage/neuromem/memory_collection/indexes/lsh_index.py
sage/neuromem/memory_collection/indexes/mock_index.py
sage/neuromem/memory_collection/indexes/segment_index.py
sage/neuromem/services/__init__.py
sage/neuromem/services/base_service.py
sage/neuromem/services/neuromem_service_factory.py
sage/neuromem/services/registry.py
sage/neuromem/services/hierarchical/__init__.py
sage/neuromem/services/hierarchical/linknote_graph_service.py
sage/neuromem/services/hierarchical/property_graph_service.py
sage/neuromem/services/hierarchical/semantic_inverted_knowledge_graph.py
sage/neuromem/services/partitional/__init__.py
sage/neuromem/services/partitional/feature_queue_segment_combination.py
sage/neuromem/services/partitional/feature_queue_summary_combination.py
sage/neuromem/services/partitional/feature_queue_vectorstore_combination.py
sage/neuromem/services/partitional/feature_summary_vectorstore_combination.py
sage/neuromem/services/partitional/fifo_queue_service.py
sage/neuromem/services/partitional/inverted_vectorstore_combination.py
sage/neuromem/services/partitional/lsh_hash_service.py
sage/neuromem/services/partitional/segment_service.py
sage/neuromem/storage_engine/__init__.py
sage/neuromem/storage_engine/metadata_storage.py
isage_neuromem-0.2.1.1.dist-info/METADATA
isage_neuromem-0.2.1.1.dist-info/WHEEL
isage_neuromem-0.2.1.1.dist-info/top_level.txt
isage_neuromem-0.2.1.1.dist-info/RECORD
