Metadata-Version: 2.4
Name: isage-neuromem
Version: 0.2.1.1
Summary: NeuroMem - Brain-inspired memory system for AI agents with multi-modal storage
Author-email: IntelliStream Team <shuhao_zhang@hust.edu.cn>
License: Apache-2.0
Project-URL: Homepage, https://github.com/intellistream/NeuroMem
Project-URL: Documentation, https://intellistream.github.io/SAGE/
Project-URL: Repository, https://github.com/intellistream/NeuroMem
Project-URL: Bug Tracker, https://github.com/intellistream/NeuroMem/issues
Keywords: memory,ai,agents,vector-database,knowledge-graph,rag,llm
Classifier: Development Status :: 3 - Alpha
Classifier: Intended Audience :: Developers
Classifier: Intended Audience :: Science/Research
Classifier: License :: OSI Approved :: Apache Software License
Classifier: Programming Language :: Python :: 3
Classifier: Programming Language :: Python :: 3.10
Classifier: Programming Language :: Python :: 3.11
Classifier: Programming Language :: Python :: 3.12
Classifier: Topic :: Scientific/Engineering :: Artificial Intelligence
Classifier: Topic :: Database
Requires-Python: >=3.10
License-File: LICENSE
Requires-Dist: isage-common[embedding]
Requires-Dist: isage-vdb
Requires-Dist: isage-kernel
Requires-Dist: numpy<2.3.0,>=1.26.0
Requires-Dist: pyyaml<7.0,>=6.0
Requires-Dist: networkx<4.0,>=3.0
Requires-Dist: python-dateutil>=2.8.0
Requires-Dist: bm25s>=0.1.0
Requires-Dist: PyStemmer>=2.0.0
Requires-Dist: faiss-cpu>=1.7.0
Requires-Dist: datasketch>=1.5.0
Requires-Dist: redis<6.0.0,>=5.0.0
Requires-Dist: neo4j<6.0.0,>=5.0.0
Provides-Extra: benchmark
Requires-Dist: isage-data; extra == "benchmark"
Requires-Dist: isage-platform; extra == "benchmark"
Requires-Dist: pandas>=2.0.0; extra == "benchmark"
Requires-Dist: pyarrow>=10.0.0; extra == "benchmark"
Requires-Dist: matplotlib>=3.7.0; extra == "benchmark"
Requires-Dist: nltk>=3.8.0; extra == "benchmark"
Requires-Dist: openai>=1.0.0; extra == "benchmark"
Requires-Dist: psutil>=5.9.0; extra == "benchmark"
Requires-Dist: pytest>=7.0.0; extra == "benchmark"
Requires-Dist: pytest-cov>=4.0.0; extra == "benchmark"
Requires-Dist: pytest-benchmark>=4.0.0; extra == "benchmark"
Requires-Dist: ruff>=0.1.0; extra == "benchmark"
Requires-Dist: mypy>=1.0.0; extra == "benchmark"
Requires-Dist: pre-commit>=3.0.0; extra == "benchmark"
Dynamic: license-file
